newspipe/__init__.py
newspipe/apps.py
newspipe/celery.py
newspipe/urls.py
newspipe/wsgi.py
newspipe/settings/__init__.py
newspipe/settings/defaults.py
newspipe/settings/develop.py
newspipe/settings/production.py
newspipe-0.1.0.dist-info/LICENSE
newspipe-0.1.0.dist-info/METADATA
newspipe-0.1.0.dist-info/WHEEL
newspipe-0.1.0.dist-info/top_level.txt
newspipe-0.1.0.dist-info/RECORD
